xaitk_jatic/__init__.py
xaitk_jatic/interop/__init__.py
xaitk_jatic/interop/image_classification/__init__.py
xaitk_jatic/interop/image_classification/model.py
xaitk_jatic/interop/object_detection/__init__.py
xaitk_jatic/interop/object_detection/dataset.py
xaitk_jatic/interop/object_detection/model.py
xaitk_jatic/py.typed
xaitk_jatic/utils/__init__.py
xaitk_jatic/utils/bin/__init__.py
xaitk_jatic/utils/bin/sal_on_coco_dets.py
xaitk_jatic/utils/sal_on_dets.py
xaitk_jatic-0.8.0.dist-info/LICENSE
xaitk_jatic-0.8.0.dist-info/METADATA
xaitk_jatic-0.8.0.dist-info/WHEEL
xaitk_jatic-0.8.0.dist-info/entry_points.txt
xaitk_jatic-0.8.0.dist-info/RECORD
