Metadata-Version: 2.1
Name: xaitk-jatic
Version: 0.8.0
Summary: Integration package to support interfacing, implementation and example needs for the JATIC.
License: Apache-2.0
Author: Kitware, Inc.
Author-email: xaitk@kitware.com
Requires-Python: >=3.10,<4.0
Classifier: Development Status :: 3 - Alpha
Classifier: Intended Audience :: Developers
Classifier: Intended Audience :: Science/Research
Classifier: License :: OSI Approved :: Apache Software License
Classifier: Operating System :: MacOS :: MacOS X
Classifier: Operating System :: Unix
Classifier: Programming Language :: Python :: 3
Classifier: Programming Language :: Python :: 3.10
Classifier: Programming Language :: Python :: 3.11
Classifier: Programming Language :: Python :: 3.12
Classifier: Programming Language :: Python :: 3.13
Provides-Extra: docker
Provides-Extra: tools
Requires-Dist: kwcoco (>=0.2.18) ; extra == "tools"
Requires-Dist: maite (>=0.8.2,<0.9.0)
Requires-Dist: matplotlib (>=3.4.1) ; extra == "tools" or extra == "docker"
Requires-Dist: numpy (>=1.25,<2.0) ; python_version < "3.12"
Requires-Dist: numpy (>=2.1) ; python_version >= "3.13"
Requires-Dist: scipy (>=1.10.0)
Requires-Dist: setuptools (>=78.1.1)
Requires-Dist: timm (>=1.0.7,<2.0.0) ; extra == "docker"
Requires-Dist: torch (>=2.2.0) ; extra == "docker"
Requires-Dist: torchvision (>=0.21.0) ; extra == "docker"
Requires-Dist: transformers (>=4.52.1) ; extra == "docker"
Requires-Dist: xaitk-saliency (>=0.14.1)
Project-URL: Documentation, https://xaitk-jatic.readthedocs.io/
